chaotic_maps/__init__.py
chaotic_maps/map_library.py
chaotic_maps/visualizations.py
chaotic_maps-0.1.dist-info/LICENSE
chaotic_maps-0.1.dist-info/METADATA
chaotic_maps-0.1.dist-info/WHEEL
chaotic_maps-0.1.dist-info/top_level.txt
chaotic_maps-0.1.dist-info/RECORD
